setup.py
examples/notebooks/run_server.py
examples/wip/debug_layers.py
examples/wip/trk_to_annot.py
ngtools/__init__.py
ngtools/_version.py
ngtools/cmdata.py
ngtools/dandifs.py
ngtools/datasources.py
ngtools/layers.py
ngtools/opener.py
ngtools/optionals.py
ngtools/protocols.py
ngtools/scene.py
ngtools/shaders.py
ngtools/spaces.py
ngtools/transforms.py
ngtools/typing.py
ngtools/units.py
ngtools/utils.py
ngtools/_lta/__init__.py
ngtools/_lta/basis.py
ngtools/_lta/conversions.py
ngtools/_lta/expm.py
ngtools/_lta/fsutils.py
ngtools/_lta/layout.py
ngtools/_lta/lie.py
ngtools/_lta/lta.py
ngtools/_lta/utils.py
ngtools/_nglite/__init__.py
ngtools/_nglite/async_util.py
ngtools/_nglite/boss_credentials.py
ngtools/_nglite/chunks.py
ngtools/_nglite/cli.py
ngtools/_nglite/coordinate_space.py
ngtools/_nglite/credentials_provider.py
ngtools/_nglite/default_credentials_manager.py
ngtools/_nglite/downsample.py
ngtools/_nglite/downsample_scales.py
ngtools/_nglite/dvid_credentials.py
ngtools/_nglite/equivalence_map.py
ngtools/_nglite/futures.py
ngtools/_nglite/google_credentials.py
ngtools/_nglite/json_utils.py
ngtools/_nglite/json_wrappers.py
ngtools/_nglite/local_volume.py
ngtools/_nglite/random_token.py
ngtools/_nglite/read_precomputed_annotations.py
ngtools/_nglite/screenshot.py
ngtools/_nglite/segment_colors.py
ngtools/_nglite/server.py
ngtools/_nglite/skeleton.py
ngtools/_nglite/static_file_server.py
ngtools/_nglite/test_util.py
ngtools/_nglite/test_utils.py
ngtools/_nglite/trackable_state.py
ngtools/_nglite/url_state.py
ngtools/_nglite/viewer.py
ngtools/_nglite/viewer_base.py
ngtools/_nglite/viewer_config_state.py
ngtools/_nglite/viewer_state.py
ngtools/_nglite/webdriver.py
ngtools/_nglite/write_annotations.py
ngtools/_nglite/static/__init__.py
ngtools/_nglite/tool/__init__.py
ngtools/_nglite/tool/agglomeration_split_tool.py
ngtools/_nglite/tool/cube.py
ngtools/_nglite/tool/filter_bodies.py
ngtools/_nglite/tool/mask_tool.py
ngtools/_nglite/tool/merge_tool.py
ngtools_pyodide-0.0.0b7.dist-info/licenses/LICENSE
ngtools_pyodide-0.0.0b7.dist-info/METADATA
ngtools_pyodide-0.0.0b7.dist-info/WHEEL
ngtools_pyodide-0.0.0b7.dist-info/entry_points.txt
ngtools_pyodide-0.0.0b7.dist-info/top_level.txt
ngtools_pyodide-0.0.0b7.dist-info/RECORD
